opine/__init__.py
opine/__main__.py
opine/main.py
opine/metadata.py
opine/setup_and_metadata.py
opine/types.py
opine/suggestions/__init__.py
opine/suggestions/move_coverage_ini.py
opine/suggestions/move_setup_py_to_declarative.py
opine/suggestions/move_setup_requires.py
opine/suggestions/move_tox_ini.py
opine/suggestions/tests/__init__.py
opine/suggestions/tests/move_setup_py_to_declarative.py
opine/suggestions/tests/move_setup_requires.py
opine/tests/__init__.py
opine/tests/__main__.py
opine/tests/functional.py
opine/tests/metadata.py
opine/tests/setup_and_metadata.py
opine/tests/types.py
opine-0.6.0.dist-info/LICENSE
opine-0.6.0.dist-info/METADATA
opine-0.6.0.dist-info/WHEEL
opine-0.6.0.dist-info/entry_points.txt
opine-0.6.0.dist-info/top_level.txt
opine-0.6.0.dist-info/RECORD
