Metadata-Version: 2.1
Name: opine
Version: 0.6.0
Summary: An opinionated linter for python packaging
Home-page: https://github.com/python-packaging/opine/
Author: Tim Hatch
Author-email: tim@timhatch.com
License: MIT
Classifier: Development Status :: 4 - Beta
Requires-Python: >=3.8
License-File: LICENSE
Requires-Dist: dowsing >=0.5.0
Requires-Dist: libcst >=1.0
Requires-Dist: pkginfo >=1.5.0.1
Requires-Dist: imperfect >=0.2.0
Requires-Dist: moreorless >=0.3.0
Requires-Dist: tomlkit >=0.5.0
Requires-Dist: setuptools >=38.3.0
